{
  "$schema": "https://json-schema.org/draft/2020-12/schema",
  "$id": "https://commonweave.earth/data/map/schema.edge.json",
  "title": "Commonweave Map Edge",
  "description": "A single relationship between two organizations on the Commonweave map. Phase 1 stub.",
  "type": "object",
  "required": [
    "id",
    "source_id",
    "target_id",
    "edge_type",
    "weight",
    "confidence",
    "derived",
    "created_at",
    "source_script"
  ],
  "properties": {
    "id": {
      "type": "string",
      "description": "Stable edge id, typically edge_<source>_<target> with the lexicographically smaller id first."
    },
    "source_id": {
      "type": "string",
      "description": "Stable id of one endpoint, e.g. org_12345."
    },
    "target_id": {
      "type": "string",
      "description": "Stable id of the other endpoint."
    },
    "edge_type": {
      "type": "string",
      "enum": [
        "verified_relationship",
        "federation_membership",
        "attestation",
        "same_section_proximity",
        "cross_section_complementarity",
        "shared_resource",
        "user_need_match"
      ],
      "description": "The kind of connection. Phase 1 only emits the two proximity types; Phase 2 adds the rest."
    },
    "weight": {
      "type": "number",
      "minimum": 0,
      "maximum": 1,
      "description": "Numeric strength of the connection in [0,1]."
    },
    "confidence": {
      "type": "string",
      "enum": [
        "high",
        "medium",
        "low"
      ]
    },
    "derived": {
      "type": "boolean",
      "description": "True if generated by an algorithm, false if a human asserted the relationship."
    },
    "evidence": {
      "type": "array",
      "description": "Pointers to the data that supports this edge. Empty for derived edges in Phase 1.",
      "items": {
        "type": "object",
        "required": [
          "type",
          "value"
        ],
        "properties": {
          "type": {
            "type": "string",
            "enum": [
              "url",
              "registry",
              "manual_note",
              "wikidata",
              "inference"
            ]
          },
          "value": {
            "type": "string"
          }
        }
      }
    },
    "explanation": {
      "type": "string",
      "description": "Plain-language description of why this edge exists."
    },
    "created_at": {
      "type": "string",
      "format": "date"
    },
    "source_script": {
      "type": "string",
      "description": "Path to the script that produced this edge."
    }
  },
  "additionalProperties": true
}